{
    "journals" : {
        "SICOMP": {
            "name": "SIAM Journal on Computing",
            "url": "https://epubs.siam.org/journal/sicomp"
        },
        "DCG": {
            "name": "Discrete & Computational Geometry",
            "url": "https://www.springer.com/journal/454"
        },
        "JGT": {
            "name": "Journal of Graph Theory",
            "url": "https://onlinelibrary.wiley.com/journal/10970118"
        },
        "SIDMA": {
            "name": "SIAM Journal on Discrete Mathematics",
            "url": "https://epubs.siam.org/journal/sidma"
        },
        "AOCO": {
            "name": "Annals of Combinatorics",
            "url": "https://www.springer.com/journal/26"
        },
        "TALG": {
            "name": "ACM Transactions on Algorithms",
            "url": "https://dl.acm.org/journal/talg"
        },
        "Adv" : {
            "name" : "Advances in Mathematics",
            "url" : "https://www.journals.elsevier.com/advances-in-mathematics"
        }
    },
    "conferences" : {
        "ICALP" : {
            "name" : "International Colloquium on Automata, Languages, and Programming",
            "2020ed" : "47"
        },
        "SODA" : {
            "name" : "SIAM Symposium on Discrete Algorithms",
            "2020ed" : "31" 
        },
        "SoCG" : {
            "name" : "Symposium on Computational Geometry",
            "2020ed" : "36"
        },
        "STACS" : {
            "name" : "Symposium on Theoretical Aspects of Computer Science",
            "2020ed" : "37"
        },
        "FUN" : {
            "name" : "International Conference on Fun with Algorithms",
            "2020ed" : "9"
        },
        "MFCS" : {
            "name" : "Mathematical Foundations of Computer Science",
            "2020ed" : "45"
        },
        "STOC" : {
            "name" : "ACM Symposium on Theory of Computing",
            "2020ed" : "52"
        },
        "FOCS" : {
            "name" : "IEEE Symposium on Foundations of Computer Science",
            "2020ed" : "61"
        },
        "WALCOM" : {
            "name" : "Workshop on Algorithms and Computation",
            "2020ed" : "14"
        },
        "ISAAC" : {
            "name" : "International Symposium on Algorithms and Computation",
            "2020ed" : "31"
        },
        "WINE" : {
            "name" : "Workshop on Internet and Network Economics",
            "2020ed" : "16"
        }
    }
}